{
    "case_id": "IN-BAIL-2023-0616",
    "timestamp": "2023-01-01",
    "case_type": "Criminal Defense",
    "title": "High Court Bail Docket IN-BAIL-2023-0616",
    "summary": "The case involves allegations that Sameera Fatema befriended the informant via Facebook, developed a relationship, and later married him before demanding \u20b950 lakhs and extorting \u20b910 lakhs through threats and blackmail using intimate photographs. The informant alleged a pattern of similar conduct ...",
    "flags": {
        "region": "India",
        "bail_case": true
    }
}