{
    "case_id": "IN-BAIL-2023-0299",
    "timestamp": "2023-01-01",
    "case_type": "Criminal Defense",
    "title": "High Court Bail Docket IN-BAIL-2023-0299",
    "summary": "On 12 October 2012, police patrolling near a railway underbridge in Mysore found seven individuals near a Tata Safari vehicle with clubs and iron rods. They were apprehended and disclosed that they had gathered from Maharashtra to commit dacoity.",
    "flags": {
        "region": "India",
        "bail_case": true
    }
}